{
	"ulid": "01FNSABGHXPES6R3386VG3C4D1",
	"minTime": 1638208800000,
	"maxTime": 1638252000000,
	"stats": {
		"numSamples": 1021542,
		"numSeries": 761,
		"numChunks": 9038
	},
	"compaction": {
		"level": 3,
		"sources": [
			"01FNPQYR2T40C3755XYF0P6EG6",
			"01FNPYTFAQV4MAVEH307CJT0WM",
			"01FNQ5P6M1YCBJRZA1Q0CNFXGQ",
			"01FNQD1J17CH5BTT5V7BKTCE2Q",
			"01FNRWMBGSKK9YD08BHBG64EW9",
			"01FNRWN4HBSG9HD9NG78YFCC4E"
		],
		"parents": [
			{
				"ulid": "01FNQD1WB8GHS0KJYMT35CPAHP",
				"minTime": 1638208800000,
				"maxTime": 1638230400000
			},
			{
				"ulid": "01FNS3FRK08AP6WWWFN3BDAP8F",
				"minTime": 1638230400000,
				"maxTime": 1638252000000
			}
		]
	},
	"version": 1
}